<?xml version='1.0' encoding='UTF-8'?>
<song xmlns="http://openlyrics.info/namespace/2009/song" version="0.8" createdIn="OpenLP 3.1.2" modifiedIn="OpenLP 3.1.2" modifiedDate="2025-04-17T16:10:45">
  <properties>
    <titles>
      <title>Duchu Swiety przybadz z ogniem</title>
    </titles>
    <authors>
      <author>75</author>
    </authors>
  </properties>
  <lyrics>
    <verse name="v1">
      <lines>Duchu Święty, przybądź z Ogniem swym (4x)<br/>Przyjdź Duch Święty rozpal miłość w nas  (2x)<br/>rozpal miłość w nas. (2x)<br/>Duchu Święty, przybądź z mocą swą (4x)<br/>Duchu Święty, oczyść serce me (4x)<br/></lines>
    </verse>
  </lyrics>
</song>
