<?xml version='1.0' encoding='UTF-8'?>
<song xmlns="http://openlyrics.info/namespace/2009/song" version="0.8" createdIn="OpenLP 3.1.2" modifiedIn="OpenLP 3.1.2" modifiedDate="2025-04-17T16:11:01">
  <properties>
    <titles>
      <title>My Hope</title>
    </titles>
    <authors>
      <author>Paul Baloche</author>
    </authors>
  </properties>
  <lyrics>
    <verse name="v1">
      <lines>Nothin' will change if all the plans I make are wrong<br/>Your love stays the same<br/>Your light will guide me through it all<br/>I'm hangin' on, I'm leanin' in to You<br/></lines>
    </verse>
    <verse name="v2">
      <lines>Nothin' can reach the end of all Your faithfulness<br/>Your grace is with me<br/>Through every shadow, every test<br/>I'm hangin' on, I'm leanin' in to You<br/></lines>
    </verse>
    <verse name="v3">
      <lines>I don't know where You'll take me<br/>But I know You're always good<br/>My hope is built on nothin' else<br/>Than Your great love, Your righteousness<br/></lines>
    </verse>
    <verse name="v4">
      <lines>I will not walk another way<br/>I trust Your heart, I trust Your name<br/>I'm holdin' on, I'm holdin' on to You<br/></lines>
    </verse>
    <verse name="v5">
      <lines>You are my rock when storms are ragin' all along<br/>You shelter me, God<br/>I'm safe with you on solid ground<br/>I'm hangin' on, I'm leanin' in to You<br/></lines>
    </verse>
    <verse name="v6">
      <lines>I don't know where You'll take me<br/>But I know You're always good<br/>My hope is built on nothin' else<br/>Than Your great love, Your righteousness<br/></lines>
    </verse>
    <verse name="v7">
      <lines>I will not walk another way<br/>I trust Your heart, I trust Your name<br/>I'm holdin' on, I'm holdin' on to You<br/></lines>
    </verse>
    <verse name="v8">
      <lines>My hope is built on nothin' else<br/>Than Your great love, Your righteousness<br/>I will not walk another way<br/>I trust Your heart, I trust Your name<br/>I'm holdin' on, I'm holdin' on, to You<br/></lines>
    </verse>
    <verse name="v9">
      <lines>I'm holdin' on, I'm holdin' on to You<br/>I'm holdin' on, I'm holdin' on to You<br/>I'm holdin' on, I'm holdin' on to You<br/>I'm holdin' on, I'm holdin' on to You<br/></lines>
    </verse>
    <verse name="v10">
      <lines>I'm holdin' on, I'm holdin' on to You<br/>I'm holdin' on, I'm holdin' on to You<br/>I'm holdin' on, I'm holdin' on to You<br/>I'm holdin' on, I'm holdin' on to You<br/></lines>
    </verse>
    <verse name="v11">
      <lines>I'm holdin' on to You<br/>(Holdin' on to You)<br/></lines>
    </verse>
    <verse name="v12">
      <lines>My hope is built on nothin' else<br/>Than Your great love, Your righteousness<br/>I will not walk another way<br/>I trust Your heart, I trust Your name<br/></lines>
    </verse>
  </lyrics>
</song>
