<?xml version='1.0' encoding='UTF-8'?>
<song xmlns="http://openlyrics.info/namespace/2009/song" version="0.8" createdIn="OpenLP 3.1.1" modifiedIn="OpenLP 3.1.1" modifiedDate="2025-03-10T16:41:43">
  <properties>
    <titles>
      <title>Nagy a mi Urunk és nagy az</title>
    </titles>
    <verseOrder>v1 v2</verseOrder>
    <authors>
      <author>Author Unknown</author>
    </authors>
    <songbooks>
      <songbook name="Éneklő Egyház" entry="710"/>
    </songbooks>
  </properties>
  <lyrics>
    <verse name="v1">
      <lines>Nagy a mi Urunk * és nagy az Ő ereje.<br/>S bölcsességének nincsen határa. És nagy az Ő ereje.</lines>
    </verse>
    <verse name="v2">
      <lines>Dicsőség az Atyának és a Fiúnak és a Szentléleknek.</lines>
    </verse>
  </lyrics>
</song>
