<?xml version='1.0' encoding='UTF-8'?>
<song xmlns="http://openlyrics.info/namespace/2009/song" version="0.8" createdIn="OpenLP 3.1.2" modifiedIn="OpenLP 3.1.2" modifiedDate="2025-04-17T16:11:04">
  <properties>
    <titles>
      <title>Open space</title>
    </titles>
    <authors>
      <author>Housefires</author>
    </authors>
  </properties>
  <lyrics>
    <verse name="v1">
      <lines>Pull me in closer, close to Your heart<br/>May I be a pure reflection of all You are<br/></lines>
    </verse>
    <verse name="v2">
      <lines>Love that is patient, love that is kind<br/>And love that keeps no offences or wrongs in my mind<br/></lines>
    </verse>
    <verse name="v3">
      <lines>Make me like Jesus<br/>Make me like Jesus<br/></lines>
    </verse>
    <verse name="v4">
      <lines>My heart is an open space<br/>For You to come and have Your way<br/>I'm open, I'm o...o-o-o-open<br/></lines>
    </verse>
    <verse name="v5">
      <lines>My heart is an open space<br/>For You to come and have Your way<br/>I'm open, I'm o...o-o-o-open<br/></lines>
    </verse>
    <verse name="v6">
      <lines>You're faithful to find me, right where I am<br/>Though even in my wandering, You call me friend<br/></lines>
    </verse>
    <verse name="v7">
      <lines>And mercy receives me and lifts me to my feet<br/>And I'm caught up in the wonder and mystery<br/></lines>
    </verse>
    <verse name="v8">
      <lines>I'll know when Jesus<br/>I'll know when Jesus<br/></lines>
    </verse>
    <verse name="v9">
      <lines>My heart is an open space<br/>For You to come and have Your way<br/>I'm open, I'm o...o-o-o-open<br/></lines>
    </verse>
    <verse name="v10">
      <lines>My heart is an open space<br/>For You to come and have Your way<br/>I'm o...o-o-open, I'm o...o-o-o-open<br/></lines>
    </verse>
  </lyrics>
</song>
